factum/__init__.py
factum/example/__init__.py
factum/example/dag/__init__.py
factum/example/dag/nested.py
factum/example/dag/basic_1/__init__.py
factum/example/dag/basic_1/detail_1/__init__.py
factum/example/dag/basic_1/detail_2/__init__.py
factum/example/dag/basic_2/__init__.py
factum/example/dag/basic_2/detail_1/__init__.py
factum/lib/__init__.py
factum/lib/dev.py
factum/lib/objects.py
factum-0.0.5.dist-info/LICENSE
factum-0.0.5.dist-info/METADATA
factum-0.0.5.dist-info/WHEEL
factum-0.0.5.dist-info/top_level.txt
factum-0.0.5.dist-info/RECORD
