Metadata-Version: 2.1
Name: factum
Version: 0.0.5
Summary: a simple agent-inspired DAG composition and execution framework
Home-page: https://github.com/lastmeta/factum
Author: Jordan Miller
Author-email: paradoxlabs@protonmail.com
License: UNKNOWN
Platform: UNKNOWN
Classifier: Programming Language :: Python :: 3
Classifier: License :: OSI Approved :: Apache Software License
Classifier: Operating System :: OS Independent
Requires-Python: >=3.5.2
Requires-Dist: networkx
Requires-Dist: matplotlib
